Workbook

Sheet README
A1: Commercial Partnership Business Case — Live Sports Streaming Deal
A2: Hypothetical deal: a mid-tier sports league's out-of-market live-games package, benchmarked to NFL Sunday Ticket (YouTube) and MLS (Apple). Decision: Should the platform sign a 5-year exclusive license for a premium live-games package, and which deal structure maximizes long-term value?
A4: HOW TO USE
A5: 1. Inputs holds every assumption (blue text on yellow) with its source or an ASSUMPTION label. Change any input to test a different view.
A6: 2. Model, Sensitivity_Calc, Scenarios, Sensitivity, Variance_Tracking and Memo all update automatically — do not type over black formula cells.
A7: 3. Review Scenarios (NPV / IRR / payback by structure and scenario) and Sensitivity (tornado) to form your Finance Point of View.
A8: 4. Memo holds the one-page Finance Point of View; its key numbers are linked to the model. The narrative reflects the current inputs.
A10: TABS
A11: Inputs — scenario drivers (Downside/Base/Upside), general assumptions, deal terms, scenario weights, sensitivity settings.
A12: Model — full 5-year deal P&L and cash flows for each scenario (three stacked blocks), for all three deal structures.
A13: Scenarios — NPV, IRR and payback summary; probability-weighted NPV; best structure per scenario.
A14: Sensitivity — one-at-a-time driver flex on the Base case with a tornado chart. Sensitivity_Calc holds the supporting calculations.
... A31: All currency in $mm unless noted; subscribers and viewing hours in millions.

Sheet Inputs
A1: Inputs & Assumptions
A2: Yellow cells = inputs (blue text). Every value is sourced or labeled ASSUMPTION in column F. Change any input and all tabs update.
A4: SCENARIO DRIVERS | B4: Unit | C4: Downside | D4: Base | E4: Upside | F4: Source / rationale
A5: Year-1 subscribers | B5: mm | C5: 0.6 | D5: 1 | E5: 1.5 | F5: Benchmark: analyst est. ~1.5M NFL Sunday Ticket subs in its first YouTube season (Sportico, Oct 2023). Scaled down for a mid-tier league. ASSUMPTION.
A6: Annual growth (subs & viewing hours) | B6: % | C6: 0.03 | D6: 0.08 | E6: 0.15 | F6: ASSUMPTION. Downside = flat demand; upside = star-driven surge (MLS Season Pass signups jumped after Messi's 2023 arrival). Sunday Ticket hit record paid subs in 2025 (Variety, Feb 2026).
A7: Year-1 viewing hours | B7: mm hrs | C7: 90 | D7: 150 | E7: 225 | F7: Derived: subscribers × ~100 hrs/season (2 games/wk × 2 hrs × 25 wks) + ~50M hrs from free-to-view games. ASSUMPTION.
A8: Ad CPM | B8: $ | C8: 30 | D8: 40 | E8: 55 | F8: Premium live sports $30–65 CPM; less-premium sports $15–35 (StreamLayer CTV live sports guide, Jan 2026). Avg CTV CPM ~$26 and falling (Adwave, 2026) → downside $30.
A9: Cannibalization of ad viewing | B9: % | C9: 0.35 | D9: 0.25 | E9: 0.15 | F9: ASSUMPTION — share of viewing hours fans would otherwise spend on other platform content.
A11: GENERAL ASSUMPTIONS | B11: Unit | C11: Value | F11: Source / rationale
A12: Season subscription price | B12: $ / season | C12: 150 | F12: Between MLS Season Pass $99/season (Front Office Sports, Nov 2025) and NFL Sunday Ticket $276 new-user / $480 returning (Sportico, Aug 2025).
A13: Platform / payment processing fees | B13: % of sub rev | C13: 0.15 | F13: App-store subscription commission (Apple/Google, 15% standard for renewing subscriptions); web sign-ups avoid it. Verify on developer pages.
A14: Ad minutes per viewing hour | B14: min | C14: 10 | F14: Streaming 1–9 min/hr vs. ~15 min/hr linear (StackAdapt, Mar 2026); live-sports streams carry natural game breaks.
A15: Ad spots per minute | B15: # | C15: 2 | F15: 30-second spots.
A16: Ad fill rate | B16: % | C16: 0.85 | F16: ASSUMPTION — premium live inventory typically sells through; haircut for unsold breaks.
A17: Production & delivery cost, Year 1 | B17: $mm | C17: 60 | F17: ASSUMPTION — streaming delivery, production, rights operations for a mid-tier league.
A18: Cost escalator | B18: % / yr | C18: 0.03 | F18: ASSUMPTION — inflation-level.
A19: Ongoing marketing | B19: % of incr. rev | C19: 0.08 | F19: ASSUMPTION.
A20: Year-1 launch marketing | B20: $mm | C20: 50 | F20: ASSUMPTION — launch campaign scaled to deal size.
A21: Discount rate | B21: % | C21: 0.1 | F21: Alphabet WACC est. 12.74% (Aug 2026) vs. 10-yr median 8.56% (GuruFocus). 10% used as base; test the range.
A23: DEAL TERMS | B23: Unit | C23: Value | F23: Notes
A24: A: Flat license fee, Year 1 | B24: $mm | C24: 200 | F24: Between MLS–Apple (~$250M/yr: $2.5B over 10 yrs, PhoneArena) and far below NFL Sunday Ticket (~$2B/yr, CNBC Dec 2022). Domestic-only package → below MLS.
A25: A: Annual fee escalator | B25: % | C25: 0.04 | F25: 4% annual escalators assumed in analyst Sunday Ticket estimates (Sportico, Oct 2023).
A26: B: Minimum guarantee per year | B26: $mm | C26: 100 | F26: ASSUMPTION — half the flat fee; partner trades certainty for upside.
A27: B: Partner revenue share | B27: % of deal rev | C27: 0.4 | F27: ASSUMPTION — below YouTube's widely reported 55% creator ad share, since the MG already de-risks the partner.
A28: C: Partner revenue share (no MG) | B28: % of deal rev | C28: 0.6 | F28: ASSUMPTION — partner takes more share in exchange for no guarantee.
A29: Upfront signing payment (Year 0, all structures) | B29: $mm | C29: 25 | F29: ASSUMPTION — rights deals often include a signing payment; set to 0 to exclude.
A30: SCENARIO WEIGHTS & SETTINGS | C30: Value
A31: Downside probability | C31: 0.25 | F31: ASSUMPTION
A32: Base probability | C32: 0.5 | F32: ASSUMPTION
A33: Upside probability | C33: 0.25 | F33: ASSUMPTION — weights must sum to 100%
A34: Sensitivity structure (1=A, 2=B, 3=C) | C34: 2 | F34: Which structure the tornado analyzes
A35: Sensitivity flex (± % of Base value) | C35: 0.2 | F35: Each driver moved up/down by this % one at a time
A36: Variance flag threshold | C36: 0.1 | F36: Replace with your MAD-based thresholds when you connect your engine
A37: Weights check (must = 100%) | C37: =C31+C32+C33 -> 1 | D37: =IF(ABS(C37-1)<0.0001,"OK","FIX WEIGHTS") -> OK

Sheet Scenarios
A1: Scenario Summary
A3: NPV ($mm) | B3: Downside | C3: Base | D3: Upside | E3: Prob-weighted
A4: A: Flat license fee | B4: =Model!$I$21 -> -734.22429 | C4: =Model!$I$46 -> -303.16311 | D4: =Model!$I$71 -> 568.9976 | E4: =B4*Inputs!$C$31+C4*Inputs!$C$32+D4*Inputs!$C$33 -> -192.88823
A5: B: MG + revenue share | B5: =Model!$I$22 -> -298.12206 | C5: =Model!$I$47 -> 101.48325 | D5: =Model!$I$72 -> 584.48026 | E5: =B5*Inputs!$C$31+C5*Inputs!$C$32+D5*Inputs!$C$33 -> 122.33117
A6: C: Pure revenue share | B6: =Model!$I$23 -> -212.99434 | C6: =Model!$I$48 -> -91.541049 | D6: =Model!$I$73 -> 184.63114 | E6: =B6*Inputs!$C$31+C6*Inputs!$C$32+D6*Inputs!$C$33 -> -52.861324
A7: Best structure (highest NPV) | B7: =INDEX($A$4:$A$6,MATCH(MAX(B4:B6),B4:B6,0)) -> C: Pure revenue share | C7: =INDEX($A$4:$A$6,MATCH(MAX(C4:C6),C4:C6,0)) -> B: MG + revenue share | D7: =INDEX($A$4:$A$6,MATCH(MAX(D4:D6),D4:D6,0)) -> B: MG + revenue share | E7: =INDEX($A$4:$A$6,MATCH(MAX(E4:E6),E4:E6,0)) -> B: MG + revenue share
A9: IRR | B9: Downside | C9: Base | D9: Upside
A10: A: Flat license fee | B10: =Model!$J$21 -> n/a | C10: =Model!$J$46 -> n/a | D10: =Model!$J$71 -> 2.4780493
A11: B: MG + revenue share | B11: =Model!$J$22 -> n/a | C11: =Model!$J$47 -> 0.64705413 | D11: =Model!$J$72 -> 3.5267815
A12: C: Pure revenue share | B12: =Model!$J$23 -> n/a | C12: =Model!$J$48 -> n/a | D12: =Model!$J$73 -> 1.0017374
A14: Payback | B14: Downside | C14: Base | D14: Upside
A15: A: Flat license fee | B15: =Model!$K$21 -> Beyond Y5 | C15: =Model!$K$46 -> Beyond Y5 | D15: =Model!$K$71 -> Year 1
A16: B: MG + revenue share | B16: =Model!$K$22 -> Beyond Y5 | C16: =Model!$K$47 -> Year 3 | D16: =Model!$K$72 -> Year 1
A17: C: Pure revenue share | B17: =Model!$K$23 -> Beyond Y5 | C17: =Model!$K$48 -> Beyond Y5 | D17: =Model!$K$73 -> Year 2
A19: Reading this: compare how each structure performs across scenarios, not just in Base. A structure that wins Base but loses badly in Downside shifts risk to the platform — that trade-off is the core of your Finance POV.

Sheet Sensitivity
A1: Sensitivity (Tornado) — Base case, one driver at a time
A2: ="Structure analyzed: "&INDEX({"A: Flat fee","B: MG + rev share","C: Rev share"},Inputs!$C$34)&" | Flex: ±"&TEXT(Inputs!$C$35,"0%") -> Structure analyzed: B: MG + rev share | Flex: ±20%
A3: Base NPV ($mm) | B3: =CHOOSE(Inputs!$C$34,Model!$I$46,Model!$I$47,Model!$I$48) -> 101.48325
A5: Driver | B5: Low value | C5: High value | D5: NPV @ Low | E5: NPV @ High | F5: Δ vs Base (Low) | G5: Δ vs Base (High) | H5: Swing
A6: Year-1 subscribers | B6: =Inputs!$D$5*(1-Inputs!$C$35) -> 0.8 | C6: =Inputs!$D$5*(1+Inputs!$C$35) -> 1.2 | D6: =CHOOSE(Inputs!$C$34,Sensitivity_Calc!$I$20,Sensitivity_Calc!$I$21,Sensitivity_Calc!$I$22) -> 21.363247 | E6: =CHOOSE(Inputs!$C$34,Sensitivity_Calc!$I$45,Sensitivity_Calc!$I$46,Sensitivity_Calc!$I$47) -> 167.76571 | F6: =D6-$B$3 -> -80.12 | G6: =E6-$B$3 -> 66.282464 | H6: =ABS(E6-D6) -> 146.40246
A7: Year-1 viewing hours | B7: =Inputs!$D$7*(1-Inputs!$C$35) -> 120 | C7: =Inputs!$D$7*(1+Inputs!$C$35) -> 180 | D7: =CHOOSE(Inputs!$C$34,Sensitivity_Calc!$I$120,Sensitivity_Calc!$I$121,Sensitivity_Calc!$I$122) -> 59.016144 | E7: =CHOOSE(Inputs!$C$34,Sensitivity_Calc!$I$145,Sensitivity_Calc!$I$146,Sensitivity_Calc!$I$147) -> 135.53954 | F7: =D7-$B$3 -> -42.467103 | G7: =E7-$B$3 -> 34.056296 | H7: =ABS(E7-D7) -> 76.523398
A8: Ad CPM | B8: =Inputs!$D$8*(1-Inputs!$C$35) -> 32 | C8: =Inputs!$D$8*(1+Inputs!$C$35) -> 48 | D8: =CHOOSE(Inputs!$C$34,Sensitivity_Calc!$I$170,Sensitivity_Calc!$I$171,Sensitivity_Calc!$I$172) -> 59.016144 | E8: =CHOOSE(Inputs!$C$34,Sensitivity_Calc!$I$195,Sensitivity_Calc!$I$196,Sensitivity_Calc!$I$197) -> 135.53954 | F8: =D8-$B$3 -> -42.467103 | G8: =E8-$B$3 -> 34.056296 | H8: =ABS(E8-D8) -> 76.523398
A9: Cannibalization | B9: =Inputs!$D$9*(1-Inputs!$C$35) -> 0.2 | C9: =Inputs!$D$9*(1+Inputs!$C$35) -> 0.3 | D9: =CHOOSE(Inputs!$C$34,Sensitivity_Calc!$I$220,Sensitivity_Calc!$I$221,Sensitivity_Calc!$I$222) -> 122.04895 | E9: =CHOOSE(Inputs!$C$34,Sensitivity_Calc!$I$245,Sensitivity_Calc!$I$246,Sensitivity_Calc!$I$247) -> 80.917538 | F9: =D9-$B$3 -> 20.565708 | G9: =E9-$B$3 -> -20.565708 | H9: =ABS(E9-D9) -> 41.131417
A10: Annual growth | B10: =Inputs!$D$6*(1-Inputs!$C$35) -> 0.064 | C10: =Inputs!$D$6*(1+Inputs!$C$35) -> 0.096 | D10: =CHOOSE(Inputs!$C$34,Sensitivity_Calc!$I$70,Sensitivity_Calc!$I$71,Sensitivity_Calc!$I$72) -> 88.223891 | E10: =CHOOSE(Inputs!$C$34,Sensitivity_Calc!$I$95,Sensitivity_Calc!$I$96,Sensitivity_Calc!$I$97) -> 114.595 | F10: =D10-$B$3 -> -13.259355 | G10: =E10-$B$3 -> 13.111756 | H10: =ABS(E10-D10) -> 26.371111
A12: Largest NPV swing driver | B12: =INDEX(A6:A10,MATCH(MAX(H6:H10),H6:H10,0)) -> Year-1 subscribers
A13: Approx. breakeven Year-1 subscribers (mm) | B13: =IFERROR(Inputs!$D$5-$B$3*(C6-B6)/(E6-D6),"n/a") -> 0.72272804 | C13: Linear interpolation from the subscriber flex — the Year-1 subscriber level where NPV ≈ 0. Approximate for Structure B (MG creates a kink).
A14: Drivers are ordered by swing at current inputs (largest first). If you change inputs materially, re-check the order. Viewing hours and CPM show identical swings because ad revenue is proportional to both.

Sheet Model
A1: Deal Model by Scenario ($mm unless noted)
A2: All cells are formulas driven by Inputs. Structures: A = flat fee, B = minimum guarantee + rev share, C = pure rev share.
A4: DOWNSIDE SCENARIO | B4: Year 0 | C4: Year 1 | D4: Year 2 | E4: Year 3 | F4: Year 4 | G4: Year 5 | I4: NPV ($mm) | J4: IRR | K4: Payback
A5: Subscribers (mm) | C5: =Inputs!$C$5 -> 0.6 | D5: =C5*(1+Inputs!$C$6) -> 0.618 | E5: =D5*(1+Inputs!$C$6) -> 0.63654 | F5: =E5*(1+Inputs!$C$6) -> 0.6556362 | G5: =F5*(1+Inputs!$C$6) -> 0.67530529
A6: Gross subscription revenue | C6: =C5*Inputs!$C$12 -> 90 | D6: =D5*Inputs!$C$12 -> 92.7 | E6: =E5*Inputs!$C$12 -> 95.481 | F6: =F5*Inputs!$C$12 -> 98.34543 | G6: =G5*Inputs!$C$12 -> 101.29579
A7: Platform / payment fees | C7: =-C6*Inputs!$C$13 -> -13.5 | D7: =-D6*Inputs!$C$13 -> -13.905 | E7: =-E6*Inputs!$C$13 -> -14.32215 | F7: =-F6*Inputs!$C$13 -> -14.751815 | G7: =-G6*Inputs!$C$13 -> -15.194369
A8: Net subscription revenue | C8: =C6+C7 -> 76.5 | D8: =D6+D7 -> 78.795 | E8: =E6+E7 -> 81.15885 | F8: =F6+F7 -> 83.593615 | G8: =G6+G7 -> 86.101424
A9: Viewing hours (mm) | C9: =Inputs!$C$7 -> 90 | D9: =C9*(1+Inputs!$C$6) -> 92.7 | E9: =D9*(1+Inputs!$C$6) -> 95.481 | F9: =E9*(1+Inputs!$C$6) -> 98.34543 | G9: =F9*(1+Inputs!$C$6) -> 101.29579
A10: Ad impressions (mm) | C10: =C9*Inputs!$C$14*Inputs!$C$15 -> 1800 | D10: =D9*Inputs!$C$14*Inputs!$C$15 -> 1854 | E10: =E9*Inputs!$C$14*Inputs!$C$15 -> 1909.62 | F10: =F9*Inputs!$C$14*Inputs!$C$15 -> 1966.9086 | G10: =G9*Inputs!$C$14*Inputs!$C$15 -> 2025.9159
A11: Gross ad revenue | C11: =C10*Inputs!$C$8/1000*Inputs!$C$16 -> 45.9 | D11: =D10*Inputs!$C$8/1000*Inputs!$C$16 -> 47.277 | E11: =E10*Inputs!$C$8/1000*Inputs!$C$16 -> 48.69531 | F11: =F10*Inputs!$C$8/1000*Inputs!$C$16 -> 50.156169 | G11: =G10*Inputs!$C$8/1000*Inputs!$C$16 -> 51.660854
A12: Deal-attributable revenue (rev-share base) | C12: =C8+C11 -> 122.4 | D12: =D8+D11 -> 126.072 | E12: =E8+E11 -> 129.85416 | F12: =F8+F11 -> 133.74978 | G12: =G8+G11 -> 137.76228
A13: Less: cannibalized ad revenue | C13: =-C11*Inputs!$C$9 -> -16.065 | D13: =-D11*Inputs!$C$9 -> -16.54695 | E13: =-E11*Inputs!$C$9 -> -17.043359 | F13: =-F11*Inputs!$C$9 -> -17.554659 | G13: =-G11*Inputs!$C$9 -> -18.081299
A14: Incremental revenue to platform | C14: =C12+C13 -> 106.335 | D14: =D12+D13 -> 109.52505 | E14: =E12+E13 -> 112.8108 | F14: =F12+F13 -> 116.19513 | G14: =G12+G13 -> 119.68098
A15: Production & delivery | C15: =-Inputs!$C$17*(1+Inputs!$C$18)^0 -> -60 | D15: =-Inputs!$C$17*(1+Inputs!$C$18)^1 -> -61.8 | E15: =-Inputs!$C$17*(1+Inputs!$C$18)^2 -> -63.654 | F15: =-Inputs!$C$17*(1+Inputs!$C$18)^3 -> -65.56362 | G15: =-Inputs!$C$17*(1+Inputs!$C$18)^4 -> -67.530529
A16: Marketing | C16: =-(C14*Inputs!$C$19+Inputs!$C$20) -> -58.5068 | D16: =-(D14*Inputs!$C$19) -> -8.762004 | E16: =-(E14*Inputs!$C$19) -> -9.0248641 | F16: =-(F14*Inputs!$C$19) -> -9.29561 | G16: =-(G14*Inputs!$C$19) -> -9.5744783
A17: Contribution before partner payments | C17: =C14+C15+C16 -> -12.1718 | D17: =D14+D15+D16 -> 38.963046 | E17: =E14+E15+E16 -> 40.131937 | F17: =F14+F15+F16 -> 41.335896 | G17: =G14+G15+G16 -> 42.575972
A18: Partner payment — A: Flat fee | C18: =-Inputs!$C$24*(1+Inputs!$C$25)^0 -> -200 | D18: =-Inputs!$C$24*(1+Inputs!$C$25)^1 -> -208 | E18: =-Inputs!$C$24*(1+Inputs!$C$25)^2 -> -216.32 | F18: =-Inputs!$C$24*(1+Inputs!$C$25)^3 -> -224.9728 | G18: =-Inputs!$C$24*(1+Inputs!$C$25)^4 -> -233.97171
A19: Partner payment — B: MG + share | C19: =-MAX(Inputs!$C$26,Inputs!$C$27*C12) -> -100 | D19: =-MAX(Inputs!$C$26,Inputs!$C$27*D12) -> -100 | E19: =-MAX(Inputs!$C$26,Inputs!$C$27*E12) -> -100 | F19: =-MAX(Inputs!$C$26,Inputs!$C$27*F12) -> -100 | G19: =-MAX(Inputs!$C$26,Inputs!$C$27*G12) -> -100
A20: Partner payment — C: Rev share | C20: =-Inputs!$C$28*C12 -> -73.44 | D20: =-Inputs!$C$28*D12 -> -75.6432 | E20: =-Inputs!$C$28*E12 -> -77.912496 | F20: =-Inputs!$C$28*F12 -> -80.249871 | G20: =-Inputs!$C$28*G12 -> -82.657367
A21: Net cash flow — A | B21: =-Inputs!$C$29 -> -25 | C21: =C17+C18 -> -212.1718 | D21: =D17+D18 -> -169.03695 | E21: =E17+E18 -> -176.18806 | F21: =F17+F18 -> -183.6369 | G21: =G17+G18 -> -191.39574 | I21: =B21+NPV(Inputs!$C$21,C21:G21) -> -734.22429 | J21: =IFERROR(IRR(B21:G21),"n/a") -> n/a | K21: =IF(COUNTIF(C24:G24,"<0")>=5,"Beyond Y5","Year "&(COUNTIF(C24:G24,"<0")+1)) -> Beyond Y5
A22: Net cash flow — B | B22: =-Inputs!$C$29 -> -25 | C22: =C17+C19 -> -112.1718 | D22: =D17+D19 -> -61.036954 | E22: =E17+E19 -> -59.868063 | F22: =F17+F19 -> -58.664104 | G22: =G17+G19 -> -57.424028 | I22: =B22+NPV(Inputs!$C$21,C22:G22) -> -298.12206 | J22: =IFERROR(IRR(B22:G22),"n/a") -> n/a | K22: =IF(COUNTIF(C25:G25,"<0")>=5,"Beyond Y5","Year "&(COUNTIF(C25:G25,"<0")+1)) -> Beyond Y5
A23: Net cash flow — C | B23: =-Inputs!$C$29 -> -25 | C23: =C17+C20 -> -85.6118 | D23: =D17+D20 -> -36.680154 | E23: =E17+E20 -> -37.780559 | F23: =F17+F20 -> -38.913975 | G23: =G17+G20 -> -40.081395 | I23: =B23+NPV(Inputs!$C$21,C23:G23) -> -212.99434 | J23: =IFERROR(IRR(B23:G23),"n/a") -> n/a | K23: =IF(COUNTIF(C26:G26,"<0")>=5,"Beyond Y5","Year "&(COUNTIF(C26:G26,"<0")+1)) -> Beyond Y5
A24: Cumulative cash flow — A | C24: =B21+C21 -> -237.1718 | D24: =C24+D21 -> -406.20875 | E24: =D24+E21 -> -582.39682 | F24: =E24+F21 -> -766.03372 | G24: =F24+G21 -> -957.42946
A25: Cumulative cash flow — B | C25: =B22+C22 -> -137.1718 | D25: =C25+D22 -> -198.20875 | E25: =D25+E22 -> -258.07682 | F25: =E25+F22 -> -316.74092 | G25: =F25+G22 -> -374.16495
A26: Cumulative cash flow — C | C26: =B23+C23 -> -110.6118 | D26: =C26+D23 -> -147.29195 | E26: =D26+E23 -> -185.07251 | F26: =E26+F23 -> -223.98649 | G26: =F26+G23 -> -264.06788
A29: BASE SCENARIO | B29: Year 0 | C29: Year 1 | D29: Year 2 | E29: Year 3 | F29: Year 4 | G29: Year 5 | I29: NPV ($mm) | J29: IRR | K29: Payback
A30: Subscribers (mm) | C30: =Inputs!$D$5 -> 1 | D30: =C30*(1+Inputs!$D$6) -> 1.08 | E30: =D30*(1+Inputs!$D$6) -> 1.1664 | F30: =E30*(1+Inputs!$D$6) -> 1.259712 | G30: =F30*(1+Inputs!$D$6) -> 1.360489
A31: Gross subscription revenue | C31: =C30*Inputs!$C$12 -> 150 | D31: =D30*Inputs!$C$12 -> 162 | E31: =E30*Inputs!$C$12 -> 174.96 | F31: =F30*Inputs!$C$12 -> 188.9568 | G31: =G30*Inputs!$C$12 -> 204.07334
A32: Platform / payment fees | C32: =-C31*Inputs!$C$13 -> -22.5 | D32: =-D31*Inputs!$C$13 -> -24.3 | E32: =-E31*Inputs!$C$13 -> -26.244 | F32: =-F31*Inputs!$C$13 -> -28.34352 | G32: =-G31*Inputs!$C$13 -> -30.611002
A33: Net subscription revenue | C33: =C31+C32 -> 127.5 | D33: =D31+D32 -> 137.7 | E33: =E31+E32 -> 148.716 | F33: =F31+F32 -> 160.61328 | G33: =G31+G32 -> 173.46234
A34: Viewing hours (mm) | C34: =Inputs!$D$7 -> 150 | D34: =C34*(1+Inputs!$D$6) -> 162 | E34: =D34*(1+Inputs!$D$6) -> 174.96 | F34: =E34*(1+Inputs!$D$6) -> 188.9568 | G34: =F34*(1+Inputs!$D$6) -> 204.07334
A35: Ad impressions (mm) | C35: =C34*Inputs!$C$14*Inputs!$C$15 -> 3000 | D35: =D34*Inputs!$C$14*Inputs!$C$15 -> 3240 | E35: =E34*Inputs!$C$14*Inputs!$C$15 -> 3499.2 | F35: =F34*Inputs!$C$14*Inputs!$C$15 -> 3779.136 | G35: =G34*Inputs!$C$14*Inputs!$C$15 -> 4081.4669
A36: Gross ad revenue | C36: =C35*Inputs!$D$8/1000*Inputs!$C$16 -> 102 | D36: =D35*Inputs!$D$8/1000*Inputs!$C$16 -> 110.16 | E36: =E35*Inputs!$D$8/1000*Inputs!$C$16 -> 118.9728 | F36: =F35*Inputs!$D$8/1000*Inputs!$C$16 -> 128.49062 | G36: =G35*Inputs!$D$8/1000*Inputs!$C$16 -> 138.76987
A37: Deal-attributable revenue (rev-share base) | C37: =C33+C36 -> 229.5 | D37: =D33+D36 -> 247.86 | E37: =E33+E36 -> 267.6888 | F37: =F33+F36 -> 289.1039 | G37: =G33+G36 -> 312.23222
A38: Less: cannibalized ad revenue | C38: =-C36*Inputs!$D$9 -> -25.5 | D38: =-D36*Inputs!$D$9 -> -27.54 | E38: =-E36*Inputs!$D$9 -> -29.7432 | F38: =-F36*Inputs!$D$9 -> -32.122656 | G38: =-G36*Inputs!$D$9 -> -34.692468
A39: Incremental revenue to platform | C39: =C37+C38 -> 204 | D39: =D37+D38 -> 220.32 | E39: =E37+E38 -> 237.9456 | F39: =F37+F38 -> 256.98125 | G39: =G37+G38 -> 277.53975
A40: Production & delivery | C40: =-Inputs!$C$17*(1+Inputs!$C$18)^0 -> -60 | D40: =-Inputs!$C$17*(1+Inputs!$C$18)^1 -> -61.8 | E40: =-Inputs!$C$17*(1+Inputs!$C$18)^2 -> -63.654 | F40: =-Inputs!$C$17*(1+Inputs!$C$18)^3 -> -65.56362 | G40: =-Inputs!$C$17*(1+Inputs!$C$18)^4 -> -67.530529
A41: Marketing | C41: =-(C39*Inputs!$C$19+Inputs!$C$20) -> -66.32 | D41: =-(D39*Inputs!$C$19) -> -17.6256 | E41: =-(E39*Inputs!$C$19) -> -19.035648 | F41: =-(F39*Inputs!$C$19) -> -20.5585 | G41: =-(G39*Inputs!$C$19) -> -22.20318
A42: Contribution before partner payments | C42: =C39+C40+C41 -> 77.68 | D42: =D39+D40+D41 -> 140.8944 | E42: =E39+E40+E41 -> 155.25595 | F42: =F39+F40+F41 -> 170.85913 | G42: =G39+G40+G41 -> 187.80604
A43: Partner payment — A: Flat fee | C43: =-Inputs!$C$24*(1+Inputs!$C$25)^0 -> -200 | D43: =-Inputs!$C$24*(1+Inputs!$C$25)^1 -> -208 | E43: =-Inputs!$C$24*(1+Inputs!$C$25)^2 -> -216.32 | F43: =-Inputs!$C$24*(1+Inputs!$C$25)^3 -> -224.9728 | G43: =-Inputs!$C$24*(1+Inputs!$C$25)^4 -> -233.97171
A44: Partner payment — B: MG + share | C44: =-MAX(Inputs!$C$26,Inputs!$C$27*C37) -> -100 | D44: =-MAX(Inputs!$C$26,Inputs!$C$27*D37) -> -100 | E44: =-MAX(Inputs!$C$26,Inputs!$C$27*E37) -> -107.07552 | F44: =-MAX(Inputs!$C$26,Inputs!$C$27*F37) -> -115.64156 | G44: =-MAX(Inputs!$C$26,Inputs!$C$27*G37) -> -124.89289
A45: Partner payment — C: Rev share | C45: =-Inputs!$C$28*C37 -> -137.7 | D45: =-Inputs!$C$28*D37 -> -148.716 | E45: =-Inputs!$C$28*E37 -> -160.61328 | F45: =-Inputs!$C$28*F37 -> -173.46234 | G45: =-Inputs!$C$28*G37 -> -187.33933
A46: Net cash flow — A | B46: =-Inputs!$C$29 -> -25 | C46: =C42+C43 -> -122.32 | D46: =D42+D43 -> -67.1056 | E46: =E42+E43 -> -61.064048 | F46: =F42+F43 -> -54.113672 | G46: =G42+G43 -> -46.165673 | I46: =B46+NPV(Inputs!$C$21,C46:G46) -> -303.16311 | J46: =IFERROR(IRR(B46:G46),"n/a") -> n/a | K46: =IF(COUNTIF(C49:G49,"<0")>=5,"Beyond Y5","Year "&(COUNTIF(C49:G49,"<0")+1)) -> Beyond Y5
A47: Net cash flow — B | B47: =-Inputs!$C$29 -> -25 | C47: =C42+C44 -> -22.32 | D47: =D42+D44 -> 40.8944 | E47: =E42+E44 -> 48.180432 | F47: =F42+F44 -> 55.217567 | G47: =G42+G44 -> 62.913153 | I47: =B47+NPV(Inputs!$C$21,C47:G47) -> 101.48325 | J47: =IFERROR(IRR(B47:G47),"n/a") -> 0.64705413 | K47: =IF(COUNTIF(C50:G50,"<0")>=5,"Beyond Y5","Year "&(COUNTIF(C50:G50,"<0")+1)) -> Year 3
A48: Net cash flow — C | B48: =-Inputs!$C$29 -> -25 | C48: =C42+C45 -> -60.02 | D48: =D42+D45 -> -7.8216 | E48: =E42+E45 -> -5.357328 | F48: =F42+F45 -> -2.6032142 | G48: =G42+G45 -> 0.46670962 | I48: =B48+NPV(Inputs!$C$21,C48:G48) -> -91.541049 | J48: =IFERROR(IRR(B48:G48),"n/a") -> n/a | K48: =IF(COUNTIF(C51:G51,"<0")>=5,"Beyond Y5","Year "&(COUNTIF(C51:G51,"<0")+1)) -> Beyond Y5
A49: Cumulative cash flow — A | C49: =B46+C46 -> -147.32 | D49: =C49+D46 -> -214.4256 | E49: =D49+E46 -> -275.48965 | F49: =E49+F46 -> -329.60332 | G49: =F49+G46 -> -375.76899
A50: Cumulative cash flow — B | C50: =B47+C47 -> -47.32 | D50: =C50+D47 -> -6.4256 | E50: =D50+E47 -> 41.754832 | F50: =E50+F47 -> 96.972399 | G50: =F50+G47 -> 159.88555
A51: Cumulative cash flow — C | C51: =B48+C48 -> -85.02 | D51: =C51+D48 -> -92.8416 | E51: =D51+E48 -> -98.198928 | F51: =E51+F48 -> -100.80214 | G51: =F51+G48 -> -100.33543
A54: UPSIDE SCENARIO | B54: Year 0 | C54: Year 1 | D54: Year 2 | E54: Year 3 | F54: Year 4 | G54: Year 5 | I54: NPV ($mm) | J54: IRR | K54: Payback
A55: Subscribers (mm) | C55: =Inputs!$E$5 -> 1.5 | D55: =C55*(1+Inputs!$E$6) -> 1.725 | E55: =D55*(1+Inputs!$E$6) -> 1.98375 | F55: =E55*(1+Inputs!$E$6) -> 2.2813125 | G55: =F55*(1+Inputs!$E$6) -> 2.6235094
A56: Gross subscription revenue | C56: =C55*Inputs!$C$12 -> 225 | D56: =D55*Inputs!$C$12 -> 258.75 | E56: =E55*Inputs!$C$12 -> 297.5625 | F56: =F55*Inputs!$C$12 -> 342.19687 | G56: =G55*Inputs!$C$12 -> 393.52641
A57: Platform / payment fees | C57: =-C56*Inputs!$C$13 -> -33.75 | D57: =-D56*Inputs!$C$13 -> -38.8125 | E57: =-E56*Inputs!$C$13 -> -44.634375 | F57: =-F56*Inputs!$C$13 -> -51.329531 | G57: =-G56*Inputs!$C$13 -> -59.028961
A58: Net subscription revenue | C58: =C56+C57 -> 191.25 | D58: =D56+D57 -> 219.9375 | E58: =E56+E57 -> 252.92812 | F58: =F56+F57 -> 290.86734 | G58: =G56+G57 -> 334.49745
A59: Viewing hours (mm) | C59: =Inputs!$E$7 -> 225 | D59: =C59*(1+Inputs!$E$6) -> 258.75 | E59: =D59*(1+Inputs!$E$6) -> 297.5625 | F59: =E59*(1+Inputs!$E$6) -> 342.19687 | G59: =F59*(1+Inputs!$E$6) -> 393.52641
A60: Ad impressions (mm) | C60: =C59*Inputs!$C$14*Inputs!$C$15 -> 4500 | D60: =D59*Inputs!$C$14*Inputs!$C$15 -> 5175 | E60: =E59*Inputs!$C$14*Inputs!$C$15 -> 5951.25 | F60: =F59*Inputs!$C$14*Inputs!$C$15 -> 6843.9375 | G60: =G59*Inputs!$C$14*Inputs!$C$15 -> 7870.5281
A61: Gross ad revenue | C61: =C60*Inputs!$E$8/1000*Inputs!$C$16 -> 210.375 | D61: =D60*Inputs!$E$8/1000*Inputs!$C$16 -> 241.93125 | E61: =E60*Inputs!$E$8/1000*Inputs!$C$16 -> 278.22094 | F61: =F60*Inputs!$E$8/1000*Inputs!$C$16 -> 319.95408 | G61: =G60*Inputs!$E$8/1000*Inputs!$C$16 -> 367.94719
A62: Deal-attributable revenue (rev-share base) | C62: =C58+C61 -> 401.625 | D62: =D58+D61 -> 461.86875 | E62: =E58+E61 -> 531.14906 | F62: =F58+F61 -> 610.82142 | G62: =G58+G61 -> 702.44464
A63: Less: cannibalized ad revenue | C63: =-C61*Inputs!$E$9 -> -31.55625 | D63: =-D61*Inputs!$E$9 -> -36.289687 | E63: =-E61*Inputs!$E$9 -> -41.733141 | F63: =-F61*Inputs!$E$9 -> -47.993112 | G63: =-G61*Inputs!$E$9 -> -55.192078
A64: Incremental revenue to platform | C64: =C62+C63 -> 370.06875 | D64: =D62+D63 -> 425.57906 | E64: =E62+E63 -> 489.41592 | F64: =F62+F63 -> 562.82831 | G64: =G62+G63 -> 647.25256
A65: Production & delivery | C65: =-Inputs!$C$17*(1+Inputs!$C$18)^0 -> -60 | D65: =-Inputs!$C$17*(1+Inputs!$C$18)^1 -> -61.8 | E65: =-Inputs!$C$17*(1+Inputs!$C$18)^2 -> -63.654 | F65: =-Inputs!$C$17*(1+Inputs!$C$18)^3 -> -65.56362 | G65: =-Inputs!$C$17*(1+Inputs!$C$18)^4 -> -67.530529
A66: Marketing | C66: =-(C64*Inputs!$C$19+Inputs!$C$20) -> -79.6055 | D66: =-(D64*Inputs!$C$19) -> -34.046325 | E66: =-(E64*Inputs!$C$19) -> -39.153274 | F66: =-(F64*Inputs!$C$19) -> -45.026265 | G66: =-(G64*Inputs!$C$19) -> -51.780205
A67: Contribution before partner payments | C67: =C64+C65+C66 -> 230.46325 | D67: =D64+D65+D66 -> 329.73274 | E67: =E64+E65+E66 -> 386.60865 | F67: =F64+F65+F66 -> 452.23843 | G67: =G64+G65+G66 -> 527.94182
A68: Partner payment — A: Flat fee | C68: =-Inputs!$C$24*(1+Inputs!$C$25)^0 -> -200 | D68: =-Inputs!$C$24*(1+Inputs!$C$25)^1 -> -208 | E68: =-Inputs!$C$24*(1+Inputs!$C$25)^2 -> -216.32 | F68: =-Inputs!$C$24*(1+Inputs!$C$25)^3 -> -224.9728 | G68: =-Inputs!$C$24*(1+Inputs!$C$25)^4 -> -233.97171
A69: Partner payment — B: MG + share | C69: =-MAX(Inputs!$C$26,Inputs!$C$27*C62) -> -160.65 | D69: =-MAX(Inputs!$C$26,Inputs!$C$27*D62) -> -184.7475 | E69: =-MAX(Inputs!$C$26,Inputs!$C$27*E62) -> -212.45962 | F69: =-MAX(Inputs!$C$26,Inputs!$C$27*F62) -> -244.32857 | G69: =-MAX(Inputs!$C$26,Inputs!$C$27*G62) -> -280.97785
A70: Partner payment — C: Rev share | C70: =-Inputs!$C$28*C62 -> -240.975 | D70: =-Inputs!$C$28*D62 -> -277.12125 | E70: =-Inputs!$C$28*E62 -> -318.68944 | F70: =-Inputs!$C$28*F62 -> -366.49285 | G70: =-Inputs!$C$28*G62 -> -421.46678
A71: Net cash flow — A | B71: =-Inputs!$C$29 -> -25 | C71: =C67+C68 -> 30.46325 | D71: =D67+D68 -> 121.73274 | E71: =E67+E68 -> 170.28865 | F71: =F67+F68 -> 227.26563 | G71: =G67+G68 -> 293.97011 | I71: =B71+NPV(Inputs!$C$21,C71:G71) -> 568.9976 | J71: =IFERROR(IRR(B71:G71),"n/a") -> 2.4780493 | K71: =IF(COUNTIF(C74:G74,"<0")>=5,"Beyond Y5","Year "&(COUNTIF(C74:G74,"<0")+1)) -> Year 1
A72: Net cash flow — B | B72: =-Inputs!$C$29 -> -25 | C72: =C67+C69 -> 69.81325 | D72: =D67+D69 -> 144.98524 | E72: =E67+E69 -> 174.14902 | F72: =F67+F69 -> 207.90986 | G72: =G67+G69 -> 246.96397 | I72: =B72+NPV(Inputs!$C$21,C72:G72) -> 584.48026 | J72: =IFERROR(IRR(B72:G72),"n/a") -> 3.5267815 | K72: =IF(COUNTIF(C75:G75,"<0")>=5,"Beyond Y5","Year "&(COUNTIF(C75:G75,"<0")+1)) -> Year 1
A73: Net cash flow — C | B73: =-Inputs!$C$29 -> -25 | C73: =C67+C70 -> -10.51175 | D73: =D67+D70 -> 52.611488 | E73: =E67+E70 -> 67.919211 | F73: =F67+F70 -> 85.745572 | G73: =G67+G70 -> 106.47504 | I73: =B73+NPV(Inputs!$C$21,C73:G73) -> 184.63114 | J73: =IFERROR(IRR(B73:G73),"n/a") -> 1.0017374 | K73: =IF(COUNTIF(C76:G76,"<0")>=5,"Beyond Y5","Year "&(COUNTIF(C76:G76,"<0")+1)) -> Year 2
A74: Cumulative cash flow — A | C74: =B71+C71 -> 5.46325 | D74: =C74+D71 -> 127.19599 | E74: =D74+E71 -> 297.48464 | F74: =E74+F71 -> 524.75026 | G74: =F74+G71 -> 818.72037
A75: Cumulative cash flow — B | C75: =B72+C72 -> 44.81325 | D75: =C75+D72 -> 189.79849 | E75: =D75+E72 -> 363.94751 | F75: =E75+F72 -> 571.85737 | G75: =F75+G72 -> 818.82134
A76: Cumulative cash flow — C | C76: =B73+C73 -> -35.51175 | D76: =C76+D73 -> 17.099737 | E76: =D76+E73 -> 85.018948 | F76: =E76+F73 -> 170.76452 | G76: =F76+G73 -> 277.23956

Sheet Sensitivity_Calc
A1: Sensitivity supporting calculations — Base case with one driver flexed at a time
A3: YEAR-1 SUBSCRIBERS — LOW | B3: Year 0 | C3: Year 1 | D3: Year 2 | E3: Year 3 | F3: Year 4 | G3: Year 5 | I3: NPV ($mm) | J3: IRR | K3: Payback
A4: Subscribers (mm) | C4: =(Inputs!$D$5*(1-Inputs!$C$35)) -> 0.8 | D4: =C4*(1+Inputs!$D$6) -> 0.864 | E4: =D4*(1+Inputs!$D$6) -> 0.93312 | F4: =E4*(1+Inputs!$D$6) -> 1.0077696 | G4: =F4*(1+Inputs!$D$6) -> 1.0883912
A5: Gross subscription revenue | C5: =C4*Inputs!$C$12 -> 120 | D5: =D4*Inputs!$C$12 -> 129.6 | E5: =E4*Inputs!$C$12 -> 139.968 | F5: =F4*Inputs!$C$12 -> 151.16544 | G5: =G4*Inputs!$C$12 -> 163.25868
A6: Platform / payment fees | C6: =-C5*Inputs!$C$13 -> -18 | D6: =-D5*Inputs!$C$13 -> -19.44 | E6: =-E5*Inputs!$C$13 -> -20.9952 | F6: =-F5*Inputs!$C$13 -> -22.674816 | G6: =-G5*Inputs!$C$13 -> -24.488801
A7: Net subscription revenue | C7: =C5+C6 -> 102 | D7: =D5+D6 -> 110.16 | E7: =E5+E6 -> 118.9728 | F7: =F5+F6 -> 128.49062 | G7: =G5+G6 -> 138.76987
A8: Viewing hours (mm) | C8: =Inputs!$D$7 -> 150 | D8: =C8*(1+Inputs!$D$6) -> 162 | E8: =D8*(1+Inputs!$D$6) -> 174.96 | F8: =E8*(1+Inputs!$D$6) -> 188.9568 | G8: =F8*(1+Inputs!$D$6) -> 204.07334
A9: Ad impressions (mm) | C9: =C8*Inputs!$C$14*Inputs!$C$15 -> 3000 | D9: =D8*Inputs!$C$14*Inputs!$C$15 -> 3240 | E9: =E8*Inputs!$C$14*Inputs!$C$15 -> 3499.2 | F9: =F8*Inputs!$C$14*Inputs!$C$15 -> 3779.136 | G9: =G8*Inputs!$C$14*Inputs!$C$15 -> 4081.4669
A10: Gross ad revenue | C10: =C9*Inputs!$D$8/1000*Inputs!$C$16 -> 102 | D10: =D9*Inputs!$D$8/1000*Inputs!$C$16 -> 110.16 | E10: =E9*Inputs!$D$8/1000*Inputs!$C$16 -> 118.9728 | F10: =F9*Inputs!$D$8/1000*Inputs!$C$16 -> 128.49062 | G10: =G9*Inputs!$D$8/1000*Inputs!$C$16 -> 138.76987
A11: Deal-attributable revenue (rev-share base) | C11: =C7+C10 -> 204 | D11: =D7+D10 -> 220.32 | E11: =E7+E10 -> 237.9456 | F11: =F7+F10 -> 256.98125 | G11: =G7+G10 -> 277.53975
A12: Less: cannibalized ad revenue | C12: =-C10*Inputs!$D$9 -> -25.5 | D12: =-D10*Inputs!$D$9 -> -27.54 | E12: =-E10*Inputs!$D$9 -> -29.7432 | F12: =-F10*Inputs!$D$9 -> -32.122656 | G12: =-G10*Inputs!$D$9 -> -34.692468
A13: Incremental revenue to platform | C13: =C11+C12 -> 178.5 | D13: =D11+D12 -> 192.78 | E13: =E11+E12 -> 208.2024 | F13: =F11+F12 -> 224.85859 | G13: =G11+G12 -> 242.84728
A14: Production & delivery | C14: =-Inputs!$C$17*(1+Inputs!$C$18)^0 -> -60 | D14: =-Inputs!$C$17*(1+Inputs!$C$18)^1 -> -61.8 | E14: =-Inputs!$C$17*(1+Inputs!$C$18)^2 -> -63.654 | F14: =-Inputs!$C$17*(1+Inputs!$C$18)^3 -> -65.56362 | G14: =-Inputs!$C$17*(1+Inputs!$C$18)^4 -> -67.530529
A15: Marketing | C15: =-(C13*Inputs!$C$19+Inputs!$C$20) -> -64.28 | D15: =-(D13*Inputs!$C$19) -> -15.4224 | E15: =-(E13*Inputs!$C$19) -> -16.656192 | F15: =-(F13*Inputs!$C$19) -> -17.988687 | G15: =-(G13*Inputs!$C$19) -> -19.427782
A16: Contribution before partner payments | C16: =C13+C14+C15 -> 54.22 | D16: =D13+D14+D15 -> 115.5576 | E16: =E13+E14+E15 -> 127.89221 | F16: =F13+F14+F15 -> 141.30628 | G16: =G13+G14+G15 -> 155.88897
A17: Partner payment — A: Flat fee | C17: =-Inputs!$C$24*(1+Inputs!$C$25)^0 -> -200 | D17: =-Inputs!$C$24*(1+Inputs!$C$25)^1 -> -208 | E17: =-Inputs!$C$24*(1+Inputs!$C$25)^2 -> -216.32 | F17: =-Inputs!$C$24*(1+Inputs!$C$25)^3 -> -224.9728 | G17: =-Inputs!$C$24*(1+Inputs!$C$25)^4 -> -233.97171
A18: Partner payment — B: MG + share | C18: =-MAX(Inputs!$C$26,Inputs!$C$27*C11) -> -100 | D18: =-MAX(Inputs!$C$26,Inputs!$C$27*D11) -> -100 | E18: =-MAX(Inputs!$C$26,Inputs!$C$27*E11) -> -100 | F18: =-MAX(Inputs!$C$26,Inputs!$C$27*F11) -> -102.7925 | G18: =-MAX(Inputs!$C$26,Inputs!$C$27*G11) -> -111.0159
A19: Partner payment — C: Rev share | C19: =-Inputs!$C$28*C11 -> -122.4 | D19: =-Inputs!$C$28*D11 -> -132.192 | E19: =-Inputs!$C$28*E11 -> -142.76736 | F19: =-Inputs!$C$28*F11 -> -154.18875 | G19: =-Inputs!$C$28*G11 -> -166.52385
A20: Net cash flow — A | B20: =-Inputs!$C$29 -> -25 | C20: =C16+C17 -> -145.78 | D20: =D16+D17 -> -92.4424 | E20: =E16+E17 -> -88.427792 | F20: =F16+F17 -> -83.666515 | G20: =G16+G17 -> -78.082744 | I20: =B20+NPV(Inputs!$C$21,C20:G20) -> -405.99166 | J20: =IFERROR(IRR(B20:G20),"n/a") -> n/a | K20: =IF(COUNTIF(C23:G23,"<0")>=5,"Beyond Y5","Year "&(COUNTIF(C23:G23,"<0")+1)) -> Beyond Y5
A21: Net cash flow — B | B21: =-Inputs!$C$29 -> -25 | C21: =C16+C18 -> -45.78 | D21: =D16+D18 -> 15.5576 | E21: =E16+E18 -> 27.892208 | F21: =F16+F18 -> 38.513785 | G21: =G16+G18 -> 44.873069 | I21: =B21+NPV(Inputs!$C$21,C21:G21) -> 21.363247 | J21: =IFERROR(IRR(B21:G21),"n/a") -> 0.20247158 | K21: =IF(COUNTIF(C24:G24,"<0")>=5,"Beyond Y5","Year "&(COUNTIF(C24:G24,"<0")+1)) -> Year 4
A22: Net cash flow — C | B22: =-Inputs!$C$29 -> -25 | C22: =C16+C19 -> -68.18 | D22: =D16+D19 -> -16.6344 | E22: =E16+E19 -> -14.875152 | F22: =F16+F19 -> -12.882464 | G22: =G16+G19 -> -10.63488 | I22: =B22+NPV(Inputs!$C$21,C22:G22) -> -127.3075 | J22: =IFERROR(IRR(B22:G22),"n/a") -> n/a | K22: =IF(COUNTIF(C25:G25,"<0")>=5,"Beyond Y5","Year "&(COUNTIF(C25:G25,"<0")+1)) -> Beyond Y5
A23: Cumulative cash flow — A | C23: =B20+C20 -> -170.78 | D23: =C23+D20 -> -263.2224 | E23: =D23+E20 -> -351.65019 | F23: =E23+F20 -> -435.31671 | G23: =F23+G20 -> -513.39945
A24: Cumulative cash flow — B | C24: =B21+C21 -> -70.78 | D24: =C24+D21 -> -55.2224 | E24: =D24+E21 -> -27.330192 | F24: =E24+F21 -> 11.183593 | G24: =F24+G21 -> 56.056663
A25: Cumulative cash flow — C | C25: =B22+C22 -> -93.18 | D25: =C25+D22 -> -109.8144 | E25: =D25+E22 -> -124.68955 | F25: =E25+F22 -> -137.57202 | G25: =F25+G22 -> -148.2069
A28: YEAR-1 SUBSCRIBERS — HIGH | B28: Year 0 | C28: Year 1 | D28: Year 2 | E28: Year 3 | F28: Year 4 | G28: Year 5 | I28: NPV ($mm) | J28: IRR | K28: Payback
A29: Subscribers (mm) | C29: =(Inputs!$D$5*(1+Inputs!$C$35)) -> 1.2 | D29: =C29*(1+Inputs!$D$6) -> 1.296 | E29: =D29*(1+Inputs!$D$6) -> 1.39968 | F29: =E29*(1+Inputs!$D$6) -> 1.5116544 | G29: =F29*(1+Inputs!$D$6) -> 1.6325868
A30: Gross subscription revenue | C30: =C29*Inputs!$C$12 -> 180 | D30: =D29*Inputs!$C$12 -> 194.4 | E30: =E29*Inputs!$C$12 -> 209.952 | F30: =F29*Inputs!$C$12 -> 226.74816 | G30: =G29*Inputs!$C$12 -> 244.88801
A31: Platform / payment fees | C31: =-C30*Inputs!$C$13 -> -27 | D31: =-D30*Inputs!$C$13 -> -29.16 | E31: =-E30*Inputs!$C$13 -> -31.4928 | F31: =-F30*Inputs!$C$13 -> -34.012224 | G31: =-G30*Inputs!$C$13 -> -36.733202
A32: Net subscription revenue | C32: =C30+C31 -> 153 | D32: =D30+D31 -> 165.24 | E32: =E30+E31 -> 178.4592 | F32: =F30+F31 -> 192.73594 | G32: =G30+G31 -> 208.15481
A33: Viewing hours (mm) | C33: =Inputs!$D$7 -> 150 | D33: =C33*(1+Inputs!$D$6) -> 162 | E33: =D33*(1+Inputs!$D$6) -> 174.96 | F33: =E33*(1+Inputs!$D$6) -> 188.9568 | G33: =F33*(1+Inputs!$D$6) -> 204.07334
A34: Ad impressions (mm) | C34: =C33*Inputs!$C$14*Inputs!$C$15 -> 3000 | D34: =D33*Inputs!$C$14*Inputs!$C$15 -> 3240 | E34: =E33*Inputs!$C$14*Inputs!$C$15 -> 3499.2 | F34: =F33*Inputs!$C$14*Inputs!$C$15 -> 3779.136 | G34: =G33*Inputs!$C$14*Inputs!$C$15 -> 4081.4669
A35: Gross ad revenue | C35: =C34*Inputs!$D$8/1000*Inputs!$C$16 -> 102 | D35: =D34*Inputs!$D$8/1000*Inputs!$C$16 -> 110.16 | E35: =E34*Inputs!$D$8/1000*Inputs!$C$16 -> 118.9728 | F35: =F34*Inputs!$D$8/1000*Inputs!$C$16 -> 128.49062 | G35: =G34*Inputs!$D$8/1000*Inputs!$C$16 -> 138.76987
A36: Deal-attributable revenue (rev-share base) | C36: =C32+C35 -> 255 | D36: =D32+D35 -> 275.4 | E36: =E32+E35 -> 297.432 | F36: =F32+F35 -> 321.22656 | G36: =G32+G35 -> 346.92468
A37: Less: cannibalized ad revenue | C37: =-C35*Inputs!$D$9 -> -25.5 | D37: =-D35*Inputs!$D$9 -> -27.54 | E37: =-E35*Inputs!$D$9 -> -29.7432 | F37: =-F35*Inputs!$D$9 -> -32.122656 | G37: =-G35*Inputs!$D$9 -> -34.692468
A38: Incremental revenue to platform | C38: =C36+C37 -> 229.5 | D38: =D36+D37 -> 247.86 | E38: =E36+E37 -> 267.6888 | F38: =F36+F37 -> 289.1039 | G38: =G36+G37 -> 312.23222
A39: Production & delivery | C39: =-Inputs!$C$17*(1+Inputs!$C$18)^0 -> -60 | D39: =-Inputs!$C$17*(1+Inputs!$C$18)^1 -> -61.8 | E39: =-Inputs!$C$17*(1+Inputs!$C$18)^2 -> -63.654 | F39: =-Inputs!$C$17*(1+Inputs!$C$18)^3 -> -65.56362 | G39: =-Inputs!$C$17*(1+Inputs!$C$18)^4 -> -67.530529
A40: Marketing | C40: =-(C38*Inputs!$C$19+Inputs!$C$20) -> -68.36 | D40: =-(D38*Inputs!$C$19) -> -19.8288 | E40: =-(E38*Inputs!$C$19) -> -21.415104 | F40: =-(F38*Inputs!$C$19) -> -23.128312 | G40: =-(G38*Inputs!$C$19) -> -24.978577
A41: Contribution before partner payments | C41: =C38+C39+C40 -> 101.14 | D41: =D38+D39+D40 -> 166.2312 | E41: =E38+E39+E40 -> 182.6197 | F41: =F38+F39+F40 -> 200.41197 | G41: =G38+G39+G40 -> 219.72311
A42: Partner payment — A: Flat fee | C42: =-Inputs!$C$24*(1+Inputs!$C$25)^0 -> -200 | D42: =-Inputs!$C$24*(1+Inputs!$C$25)^1 -> -208 | E42: =-Inputs!$C$24*(1+Inputs!$C$25)^2 -> -216.32 | F42: =-Inputs!$C$24*(1+Inputs!$C$25)^3 -> -224.9728 | G42: =-Inputs!$C$24*(1+Inputs!$C$25)^4 -> -233.97171
A43: Partner payment — B: MG + share | C43: =-MAX(Inputs!$C$26,Inputs!$C$27*C36) -> -102 | D43: =-MAX(Inputs!$C$26,Inputs!$C$27*D36) -> -110.16 | E43: =-MAX(Inputs!$C$26,Inputs!$C$27*E36) -> -118.9728 | F43: =-MAX(Inputs!$C$26,Inputs!$C$27*F36) -> -128.49062 | G43: =-MAX(Inputs!$C$26,Inputs!$C$27*G36) -> -138.76987
A44: Partner payment — C: Rev share | C44: =-Inputs!$C$28*C36 -> -153 | D44: =-Inputs!$C$28*D36 -> -165.24 | E44: =-Inputs!$C$28*E36 -> -178.4592 | F44: =-Inputs!$C$28*F36 -> -192.73594 | G44: =-Inputs!$C$28*G36 -> -208.15481
A45: Net cash flow — A | B45: =-Inputs!$C$29 -> -25 | C45: =C41+C42 -> -98.86 | D45: =D41+D42 -> -41.7688 | E45: =E41+E42 -> -33.700304 | F45: =F41+F42 -> -24.560828 | G45: =G41+G42 -> -14.248602 | I45: =B45+NPV(Inputs!$C$21,C45:G45) -> -200.33457 | J45: =IFERROR(IRR(B45:G45),"n/a") -> n/a | K45: =IF(COUNTIF(C48:G48,"<0")>=5,"Beyond Y5","Year "&(COUNTIF(C48:G48,"<0")+1)) -> Beyond Y5
A46: Net cash flow — B | B46: =-Inputs!$C$29 -> -25 | C46: =C41+C43 -> -0.86 | D46: =D41+D43 -> 56.0712 | E46: =E41+E43 -> 63.646896 | F46: =F41+F43 -> 71.921348 | G46: =G41+G43 -> 80.953236 | I46: =B46+NPV(Inputs!$C$21,C46:G46) -> 167.76571 | J46: =IFERROR(IRR(B46:G46),"n/a") -> 1.0957747 | K46: =IF(COUNTIF(C49:G49,"<0")>=5,"Beyond Y5","Year "&(COUNTIF(C49:G49,"<0")+1)) -> Year 2
A47: Net cash flow — C | B47: =-Inputs!$C$29 -> -25 | C47: =C41+C44 -> -51.86 | D47: =D41+D44 -> 0.9912 | E47: =E41+E44 -> 4.160496 | F47: =F41+F44 -> 7.6760357 | G47: =G41+G44 -> 11.5683 | I47: =B47+NPV(Inputs!$C$21,C47:G47) -> -55.774599 | J47: =IFERROR(IRR(B47:G47),"n/a") -> -3.063966 | K47: =IF(COUNTIF(C50:G50,"<0")>=5,"Beyond Y5","Year "&(COUNTIF(C50:G50,"<0")+1)) -> Beyond Y5
A48: Cumulative cash flow — A | C48: =B45+C45 -> -123.86 | D48: =C48+D45 -> -165.6288 | E48: =D48+E45 -> -199.3291 | F48: =E48+F45 -> -223.88993 | G48: =F48+G45 -> -238.13853
A49: Cumulative cash flow — B | C49: =B46+C46 -> -25.86 | D49: =C49+D46 -> 30.2112 | E49: =D49+E46 -> 93.858096 | F49: =E49+F46 -> 165.77944 | G49: =F49+G46 -> 246.73268
A50: Cumulative cash flow — C | C50: =B47+C47 -> -76.86 | D50: =C50+D47 -> -75.8688 | E50: =D50+E47 -> -71.708304 | F50: =E50+F47 -> -64.032268 | G50: =F50+G47 -> -52.463969
A53: ANNUAL GROWTH — LOW | B53: Year 0 | C53: Year 1 | D53: Year 2 | E53: Year 3 | F53: Year 4 | G53: Year 5 | I53: NPV ($mm) | J53: IRR | K53: Payback
A54: Subscribers (mm) | C54: =Inputs!$D$5 -> 1 | D54: =C54*(1+(Inputs!$D$6*(1-Inputs!$C$35))) -> 1.064 | E54: =D54*(1+(Inputs!$D$6*(1-Inputs!$C$35))) -> 1.132096 | F54: =E54*(1+(Inputs!$D$6*(1-Inputs!$C$35))) -> 1.2045501 | G54: =F54*(1+(Inputs!$D$6*(1-Inputs!$C$35))) -> 1.2816414
A55: Gross subscription revenue | C55: =C54*Inputs!$C$12 -> 150 | D55: =D54*Inputs!$C$12 -> 159.6 | E55: =E54*Inputs!$C$12 -> 169.8144 | F55: =F54*Inputs!$C$12 -> 180.68252 | G55: =G54*Inputs!$C$12 -> 192.2462
A56: Platform / payment fees | C56: =-C55*Inputs!$C$13 -> -22.5 | D56: =-D55*Inputs!$C$13 -> -23.94 | E56: =-E55*Inputs!$C$13 -> -25.47216 | F56: =-F55*Inputs!$C$13 -> -27.102378 | G56: =-G55*Inputs!$C$13 -> -28.83693
A57: Net subscription revenue | C57: =C55+C56 -> 127.5 | D57: =D55+D56 -> 135.66 | E57: =E55+E56 -> 144.34224 | F57: =F55+F56 -> 153.58014 | G57: =G55+G56 -> 163.40927
A58: Viewing hours (mm) | C58: =Inputs!$D$7 -> 150 | D58: =C58*(1+(Inputs!$D$6*(1-Inputs!$C$35))) -> 159.6 | E58: =D58*(1+(Inputs!$D$6*(1-Inputs!$C$35))) -> 169.8144 | F58: =E58*(1+(Inputs!$D$6*(1-Inputs!$C$35))) -> 180.68252 | G58: =F58*(1+(Inputs!$D$6*(1-Inputs!$C$35))) -> 192.2462
A59: Ad impressions (mm) | C59: =C58*Inputs!$C$14*Inputs!$C$15 -> 3000 | D59: =D58*Inputs!$C$14*Inputs!$C$15 -> 3192 | E59: =E58*Inputs!$C$14*Inputs!$C$15 -> 3396.288 | F59: =F58*Inputs!$C$14*Inputs!$C$15 -> 3613.6504 | G59: =G58*Inputs!$C$14*Inputs!$C$15 -> 3844.9241
A60: Gross ad revenue | C60: =C59*Inputs!$D$8/1000*Inputs!$C$16 -> 102 | D60: =D59*Inputs!$D$8/1000*Inputs!$C$16 -> 108.528 | E60: =E59*Inputs!$D$8/1000*Inputs!$C$16 -> 115.47379 | F60: =F59*Inputs!$D$8/1000*Inputs!$C$16 -> 122.86411 | G60: =G59*Inputs!$D$8/1000*Inputs!$C$16 -> 130.72742
A61: Deal-attributable revenue (rev-share base) | C61: =C57+C60 -> 229.5 | D61: =D57+D60 -> 244.188 | E61: =E57+E60 -> 259.81603 | F61: =F57+F60 -> 276.44426 | G61: =G57+G60 -> 294.13669
A62: Less: cannibalized ad revenue | C62: =-C60*Inputs!$D$9 -> -25.5 | D62: =-D60*Inputs!$D$9 -> -27.132 | E62: =-E60*Inputs!$D$9 -> -28.868448 | F62: =-F60*Inputs!$D$9 -> -30.716029 | G62: =-G60*Inputs!$D$9 -> -32.681855
A63: Incremental revenue to platform | C63: =C61+C62 -> 204 | D63: =D61+D62 -> 217.056 | E63: =E61+E62 -> 230.94758 | F63: =F61+F62 -> 245.72823 | G63: =G61+G62 -> 261.45484
A64: Production & delivery | C64: =-Inputs!$C$17*(1+Inputs!$C$18)^0 -> -60 | D64: =-Inputs!$C$17*(1+Inputs!$C$18)^1 -> -61.8 | E64: =-Inputs!$C$17*(1+Inputs!$C$18)^2 -> -63.654 | F64: =-Inputs!$C$17*(1+Inputs!$C$18)^3 -> -65.56362 | G64: =-Inputs!$C$17*(1+Inputs!$C$18)^4 -> -67.530529
A65: Marketing | C65: =-(C63*Inputs!$C$19+Inputs!$C$20) -> -66.32 | D65: =-(D63*Inputs!$C$19) -> -17.36448 | E65: =-(E63*Inputs!$C$19) -> -18.475807 | F65: =-(F63*Inputs!$C$19) -> -19.658258 | G65: =-(G63*Inputs!$C$19) -> -20.916387
A66: Contribution before partner payments | C66: =C63+C64+C65 -> 77.68 | D66: =D63+D64+D65 -> 137.89152 | E66: =E63+E64+E65 -> 148.81778 | F66: =F63+F64+F65 -> 160.50635 | G66: =G63+G64+G65 -> 173.00792
A67: Partner payment — A: Flat fee | C67: =-Inputs!$C$24*(1+Inputs!$C$25)^0 -> -200 | D67: =-Inputs!$C$24*(1+Inputs!$C$25)^1 -> -208 | E67: =-Inputs!$C$24*(1+Inputs!$C$25)^2 -> -216.32 | F67: =-Inputs!$C$24*(1+Inputs!$C$25)^3 -> -224.9728 | G67: =-Inputs!$C$24*(1+Inputs!$C$25)^4 -> -233.97171
A68: Partner payment — B: MG + share | C68: =-MAX(Inputs!$C$26,Inputs!$C$27*C61) -> -100 | D68: =-MAX(Inputs!$C$26,Inputs!$C$27*D61) -> -100 | E68: =-MAX(Inputs!$C$26,Inputs!$C$27*E61) -> -103.92641 | F68: =-MAX(Inputs!$C$26,Inputs!$C$27*F61) -> -110.5777 | G68: =-MAX(Inputs!$C$26,Inputs!$C$27*G61) -> -117.65468
A69: Partner payment — C: Rev share | C69: =-Inputs!$C$28*C61 -> -137.7 | D69: =-Inputs!$C$28*D61 -> -146.5128 | E69: =-Inputs!$C$28*E61 -> -155.88962 | F69: =-Inputs!$C$28*F61 -> -165.86655 | G69: =-Inputs!$C$28*G61 -> -176.48201
A70: Net cash flow — A | B70: =-Inputs!$C$29 -> -25 | C70: =C66+C67 -> -122.32 | D70: =D66+D67 -> -70.10848 | E70: =E66+E67 -> -67.502223 | F70: =F66+F67 -> -64.466449 | G70: =G66+G67 -> -60.963791 | I70: =B70+NPV(Inputs!$C$21,C70:G70) -> -326.74148 | J70: =IFERROR(IRR(B70:G70),"n/a") -> n/a | K70: =IF(COUNTIF(C73:G73,"<0")>=5,"Beyond Y5","Year "&(COUNTIF(C73:G73,"<0")+1)) -> Beyond Y5
A71: Net cash flow — B | B71: =-Inputs!$C$29 -> -25 | C71: =C66+C68 -> -22.32 | D71: =D66+D68 -> 37.89152 | E71: =E66+E68 -> 44.891364 | F71: =F66+F68 -> 49.928648 | G71: =G66+G68 -> 55.353244 | I71: =B71+NPV(Inputs!$C$21,C71:G71) -> 88.223891 | J71: =IFERROR(IRR(B71:G71),"n/a") -> 0.59560523 | K71: =IF(COUNTIF(C74:G74,"<0")>=5,"Beyond Y5","Year "&(COUNTIF(C74:G74,"<0")+1)) -> Year 3
A72: Net cash flow — C | B72: =-Inputs!$C$29 -> -25 | C72: =C66+C69 -> -60.02 | D72: =D66+D69 -> -8.62128 | E72: =E66+E69 -> -7.0718419 | F72: =F66+F69 -> -5.3602038 | G72: =G66+G69 -> -3.4740938 | I72: =B72+NPV(Inputs!$C$21,C72:G72) -> -97.820071 | J72: =IFERROR(IRR(B72:G72),"n/a") -> n/a | K72: =IF(COUNTIF(C75:G75,"<0")>=5,"Beyond Y5","Year "&(COUNTIF(C75:G75,"<0")+1)) -> Beyond Y5
A73: Cumulative cash flow — A | C73: =B70+C70 -> -147.32 | D73: =C73+D70 -> -217.42848 | E73: =D73+E70 -> -284.9307 | F73: =E73+F70 -> -349.39715 | G73: =F73+G70 -> -410.36094
A74: Cumulative cash flow — B | C74: =B71+C71 -> -47.32 | D74: =C74+D71 -> -9.42848 | E74: =D74+E71 -> 35.462884 | F74: =E74+F71 -> 85.391532 | G74: =F74+G71 -> 140.74478
A75: Cumulative cash flow — C | C75: =B72+C72 -> -85.02 | D75: =C75+D72 -> -93.64128 | E75: =D75+E72 -> -100.71312 | F75: =E75+F72 -> -106.07333 | G75: =F75+G72 -> -109.54742
A78: ANNUAL GROWTH — HIGH | B78: Year 0 | C78: Year 1 | D78: Year 2 | E78: Year 3 | F78: Year 4 | G78: Year 5 | I78: NPV ($mm) | J78: IRR | K78: Payback
A79: Subscribers (mm) | C79: =Inputs!$D$5 -> 1 | D79: =C79*(1+(Inputs!$D$6*(1+Inputs!$C$35))) -> 1.096 | E79: =D79*(1+(Inputs!$D$6*(1+Inputs!$C$35))) -> 1.201216 | F79: =E79*(1+(Inputs!$D$6*(1+Inputs!$C$35))) -> 1.3165327 | G79: =F79*(1+(Inputs!$D$6*(1+Inputs!$C$35))) -> 1.4429199
A80: Gross subscription revenue | C80: =C79*Inputs!$C$12 -> 150 | D80: =D79*Inputs!$C$12 -> 164.4 | E80: =E79*Inputs!$C$12 -> 180.1824 | F80: =F79*Inputs!$C$12 -> 197.47991 | G80: =G79*Inputs!$C$12 -> 216.43798
A81: Platform / payment fees | C81: =-C80*Inputs!$C$13 -> -22.5 | D81: =-D80*Inputs!$C$13 -> -24.66 | E81: =-E80*Inputs!$C$13 -> -27.02736 | F81: =-F80*Inputs!$C$13 -> -29.621987 | G81: =-G80*Inputs!$C$13 -> -32.465697
A82: Net subscription revenue | C82: =C80+C81 -> 127.5 | D82: =D80+D81 -> 139.74 | E82: =E80+E81 -> 153.15504 | F82: =F80+F81 -> 167.85792 | G82: =G80+G81 -> 183.97228
A83: Viewing hours (mm) | C83: =Inputs!$D$7 -> 150 | D83: =C83*(1+(Inputs!$D$6*(1+Inputs!$C$35))) -> 164.4 | E83: =D83*(1+(Inputs!$D$6*(1+Inputs!$C$35))) -> 180.1824 | F83: =E83*(1+(Inputs!$D$6*(1+Inputs!$C$35))) -> 197.47991 | G83: =F83*(1+(Inputs!$D$6*(1+Inputs!$C$35))) -> 216.43798
A84: Ad impressions (mm) | C84: =C83*Inputs!$C$14*Inputs!$C$15 -> 3000 | D84: =D83*Inputs!$C$14*Inputs!$C$15 -> 3288 | E84: =E83*Inputs!$C$14*Inputs!$C$15 -> 3603.648 | F84: =F83*Inputs!$C$14*Inputs!$C$15 -> 3949.5982 | G84: =G83*Inputs!$C$14*Inputs!$C$15 -> 4328.7596
A85: Gross ad revenue | C85: =C84*Inputs!$D$8/1000*Inputs!$C$16 -> 102 | D85: =D84*Inputs!$D$8/1000*Inputs!$C$16 -> 111.792 | E85: =E84*Inputs!$D$8/1000*Inputs!$C$16 -> 122.52403 | F85: =F84*Inputs!$D$8/1000*Inputs!$C$16 -> 134.28634 | G85: =G84*Inputs!$D$8/1000*Inputs!$C$16 -> 147.17783
A86: Deal-attributable revenue (rev-share base) | C86: =C82+C85 -> 229.5 | D86: =D82+D85 -> 251.532 | E86: =E82+E85 -> 275.67907 | F86: =F82+F85 -> 302.14426 | G86: =G82+G85 -> 331.15011
A87: Less: cannibalized ad revenue | C87: =-C85*Inputs!$D$9 -> -25.5 | D87: =-D85*Inputs!$D$9 -> -27.948 | E87: =-E85*Inputs!$D$9 -> -30.631008 | F87: =-F85*Inputs!$D$9 -> -33.571585 | G87: =-G85*Inputs!$D$9 -> -36.794457
A88: Incremental revenue to platform | C88: =C86+C87 -> 204 | D88: =D86+D87 -> 223.584 | E88: =E86+E87 -> 245.04806 | F88: =F86+F87 -> 268.57268 | G88: =G86+G87 -> 294.35566
A89: Production & delivery | C89: =-Inputs!$C$17*(1+Inputs!$C$18)^0 -> -60 | D89: =-Inputs!$C$17*(1+Inputs!$C$18)^1 -> -61.8 | E89: =-Inputs!$C$17*(1+Inputs!$C$18)^2 -> -63.654 | F89: =-Inputs!$C$17*(1+Inputs!$C$18)^3 -> -65.56362 | G89: =-Inputs!$C$17*(1+Inputs!$C$18)^4 -> -67.530529
A90: Marketing | C90: =-(C88*Inputs!$C$19+Inputs!$C$20) -> -66.32 | D90: =-(D88*Inputs!$C$19) -> -17.88672 | E90: =-(E88*Inputs!$C$19) -> -19.603845 | F90: =-(F88*Inputs!$C$19) -> -21.485814 | G90: =-(G88*Inputs!$C$19) -> -23.548452
A91: Contribution before partner payments | C91: =C88+C89+C90 -> 77.68 | D91: =D88+D89+D90 -> 143.89728 | E91: =E88+E89+E90 -> 161.79022 | F91: =F88+F89+F90 -> 181.52324 | G91: =G88+G89+G90 -> 203.27667
A92: Partner payment — A: Flat fee | C92: =-Inputs!$C$24*(1+Inputs!$C$25)^0 -> -200 | D92: =-Inputs!$C$24*(1+Inputs!$C$25)^1 -> -208 | E92: =-Inputs!$C$24*(1+Inputs!$C$25)^2 -> -216.32 | F92: =-Inputs!$C$24*(1+Inputs!$C$25)^3 -> -224.9728 | G92: =-Inputs!$C$24*(1+Inputs!$C$25)^4 -> -233.97171
A93: Partner payment — B: MG + share | C93: =-MAX(Inputs!$C$26,Inputs!$C$27*C86) -> -100 | D93: =-MAX(Inputs!$C$26,Inputs!$C$27*D86) -> -100.6128 | E93: =-MAX(Inputs!$C$26,Inputs!$C$27*E86) -> -110.27163 | F93: =-MAX(Inputs!$C$26,Inputs!$C$27*F86) -> -120.85771 | G93: =-MAX(Inputs!$C$26,Inputs!$C$27*G86) -> -132.46004
A94: Partner payment — C: Rev share | C94: =-Inputs!$C$28*C86 -> -137.7 | D94: =-Inputs!$C$28*D86 -> -150.9192 | E94: =-Inputs!$C$28*E86 -> -165.40744 | F94: =-Inputs!$C$28*F86 -> -181.28656 | G94: =-Inputs!$C$28*G86 -> -198.69007
A95: Net cash flow — A | B95: =-Inputs!$C$29 -> -25 | C95: =C91+C92 -> -122.32 | D95: =D91+D92 -> -64.10272 | E95: =E91+E92 -> -54.529781 | F95: =F91+F92 -> -43.449556 | G95: =G91+G92 -> -30.695038 | I95: =B95+NPV(Inputs!$C$21,C95:G95) -> -278.88232 | J95: =IFERROR(IRR(B95:G95),"n/a") -> n/a | K95: =IF(COUNTIF(C98:G98,"<0")>=5,"Beyond Y5","Year "&(COUNTIF(C98:G98,"<0")+1)) -> Beyond Y5
A96: Net cash flow — B | B96: =-Inputs!$C$29 -> -25 | C96: =C91+C93 -> -22.32 | D96: =D91+D93 -> 43.28448 | E96: =E91+E93 -> 51.51859 | F96: =F91+F93 -> 60.665539 | G96: =G91+G93 -> 70.816629 | I96: =B96+NPV(Inputs!$C$21,C96:G96) -> 114.595 | J96: =IFERROR(IRR(B96:G96),"n/a") -> 0.69317062 | K96: =IF(COUNTIF(C99:G99,"<0")>=5,"Beyond Y5","Year "&(COUNTIF(C99:G99,"<0")+1)) -> Year 3
A97: Net cash flow — C | B97: =-Inputs!$C$29 -> -25 | C97: =C91+C94 -> -60.02 | D97: =D91+D94 -> -7.02192 | E97: =E91+E94 -> -3.6172243 | F97: =F91+F94 -> 0.23668615 | G97: =G91+G94 -> 4.5866069 | I97: =B97+NPV(Inputs!$C$21,C97:G97) -> -85.074968 | J97: =IFERROR(IRR(B97:G97),"n/a") -> n/a | K97: =IF(COUNTIF(C100:G100,"<0")>=5,"Beyond Y5","Year "&(COUNTIF(C100:G100,"<0")+1)) -> Beyond Y5
A98: Cumulative cash flow — A | C98: =B95+C95 -> -147.32 | D98: =C98+D95 -> -211.42272 | E98: =D98+E95 -> -265.9525 | F98: =E98+F95 -> -309.40206 | G98: =F98+G95 -> -340.0971
A99: Cumulative cash flow — B | C99: =B96+C96 -> -47.32 | D99: =C99+D96 -> -4.03552 | E99: =D99+E96 -> 47.48307 | F99: =E99+F96 -> 108.14861 | G99: =F99+G96 -> 178.96524
A100: Cumulative cash flow — C | C100: =B97+C97 -> -85.02 | D100: =C100+D97 -> -92.04192 | E100: =D100+E97 -> -95.659144 | F100: =E100+F97 -> -95.422458 | G100: =F100+G97 -> -90.835851
A103: YEAR-1 VIEWING HOURS — LOW | B103: Year 0 | C103: Year 1 | D103: Year 2 | E103: Year 3 | F103: Year 4 | G103: Year 5 | I103: NPV ($mm) | J103: IRR | K103: Payback
A104: Subscribers (mm) | C104: =Inputs!$D$5 -> 1 | D104: =C104*(1+Inputs!$D$6) -> 1.08 | E104: =D104*(1+Inputs!$D$6) -> 1.1664 | F104: =E104*(1+Inputs!$D$6) -> 1.259712 | G104: =F104*(1+Inputs!$D$6) -> 1.360489
A105: Gross subscription revenue | C105: =C104*Inputs!$C$12 -> 150 | D105: =D104*Inputs!$C$12 -> 162 | E105: =E104*Inputs!$C$12 -> 174.96 | F105: =F104*Inputs!$C$12 -> 188.9568 | G105: =G104*Inputs!$C$12 -> 204.07334
A106: Platform / payment fees | C106: =-C105*Inputs!$C$13 -> -22.5 | D106: =-D105*Inputs!$C$13 -> -24.3 | E106: =-E105*Inputs!$C$13 -> -26.244 | F106: =-F105*Inputs!$C$13 -> -28.34352 | G106: =-G105*Inputs!$C$13 -> -30.611002
A107: Net subscription revenue | C107: =C105+C106 -> 127.5 | D107: =D105+D106 -> 137.7 | E107: =E105+E106 -> 148.716 | F107: =F105+F106 -> 160.61328 | G107: =G105+G106 -> 173.46234
A108: Viewing hours (mm) | C108: =(Inputs!$D$7*(1-Inputs!$C$35)) -> 120 | D108: =C108*(1+Inputs!$D$6) -> 129.6 | E108: =D108*(1+Inputs!$D$6) -> 139.968 | F108: =E108*(1+Inputs!$D$6) -> 151.16544 | G108: =F108*(1+Inputs!$D$6) -> 163.25868
A109: Ad impressions (mm) | C109: =C108*Inputs!$C$14*Inputs!$C$15 -> 2400 | D109: =D108*Inputs!$C$14*Inputs!$C$15 -> 2592 | E109: =E108*Inputs!$C$14*Inputs!$C$15 -> 2799.36 | F109: =F108*Inputs!$C$14*Inputs!$C$15 -> 3023.3088 | G109: =G108*Inputs!$C$14*Inputs!$C$15 -> 3265.1735
...

Sheet Variance_Tracking
A1: Post-Signing Performance Tracking — Plan (Base business case) vs. Actual
A2: Plan = Base-case annual incremental revenue ÷ 4. Actuals are SIMULATED (Plan × (1 + shock)) — replace with real data or feed this tab into your variance engine.
A5: Quarter | B5: Plan: incr. revenue ($mm) | C5: Simulated shock (input) | D5: Actual ($mm) | E5: Variance ($mm) | F5: Variance % | G5: Flag | H5: Driver commentary (from event log) | I5: Status
A6: Q1 | B6: =Model!C39/4 -> 51 | C6: 0.02 | D6: =B6*(1+C6) -> 52.02 | E6: =D6-B6 -> 1.02 | F6: =IF(B6=0,0,E6/B6) -> 0.02 | G6: =IF(ABS(F6)>Inputs!$C$36,"FLAG","OK") -> OK | I6: =IF(G6="OK","On track",IF(H6="","Route to analyst review","Explained — driver documented")) -> On track
A7: Q2 | B7: =Model!C39/4 -> 51 | C7: -0.04 | D7: =B7*(1+C7) -> 48.96 | E7: =D7-B7 -> -2.04 | F7: =IF(B7=0,0,E7/B7) -> -0.04 | G7: =IF(ABS(F7)>Inputs!$C$36,"FLAG","OK") -> OK | I7: =IF(G7="OK","On track",IF(H7="","Route to analyst review","Explained — driver documented")) -> On track
A8: Q3 | B8: =Model!C39/4 -> 51 | C8: -0.14 | D8: =B8*(1+C8) -> 43.86 | E8: =D8-B8 -> -7.14 | F8: =IF(B8=0,0,E8/B8) -> -0.14 | G8: =IF(ABS(F8)>Inputs!$C$36,"FLAG","OK") -> FLAG | H8: Fewer marquee games scheduled in Q3 (example) | I8: =IF(G8="OK","On track",IF(H8="","Route to analyst review","Explained — driver documented")) -> Explained — driver documented
A9: Q4 | B9: =Model!C39/4 -> 51 | C9: 0.05 | D9: =B9*(1+C9) -> 53.55 | E9: =D9-B9 -> 2.55 | F9: =IF(B9=0,0,E9/B9) -> 0.05 | G9: =IF(ABS(F9)>Inputs!$C$36,"FLAG","OK") -> OK | I9: =IF(G9="OK","On track",IF(H9="","Route to analyst review","Explained — driver documented")) -> On track
A10: Q5 | B10: =Model!D39/4 -> 55.08 | C10: 0.12 | D10: =B10*(1+C10) -> 61.6896 | E10: =D10-B10 -> 6.6096 | F10: =IF(B10=0,0,E10/B10) -> 0.12 | G10: =IF(ABS(F10)>Inputs!$C$36,"FLAG","OK") -> FLAG | I10: =IF(G10="OK","On track",IF(H10="","Route to analyst review","Explained — driver documented")) -> Route to analyst review
A11: Q6 | B11: =Model!D39/4 -> 55.08 | C11: -0.03 | D11: =B11*(1+C11) -> 53.4276 | E11: =D11-B11 -> -1.6524 | F11: =IF(B11=0,0,E11/B11) -> -0.03 | G11: =IF(ABS(F11)>Inputs!$C$36,"FLAG","OK") -> OK | I11: =IF(G11="OK","On track",IF(H11="","Route to analyst review","Explained — driver documented")) -> On track
A12: Q7 | B12: =Model!D39/4 -> 55.08 | C12: -0.18 | D12: =B12*(1+C12) -> 45.1656 | E12: =D12-B12 -> -9.9144 | F12: =IF(B12=0,0,E12/B12) -> -0.18 | G12: =IF(ABS(F12)>Inputs!$C$36,"FLAG","OK") -> FLAG | I12: =IF(G12="OK","On track",IF(H12="","Route to analyst review","Explained — driver documented")) -> Route to analyst review
A13: Q8 | B13: =Model!D39/4 -> 55.08 | C13: 0.01 | D13: =B13*(1+C13) -> 55.6308 | E13: =D13-B13 -> 0.5508 | F13: =IF(B13=0,0,E13/B13) -> 0.01 | G13: =IF(ABS(F13)>Inputs!$C$36,"FLAG","OK") -> OK | I13: =IF(G13="OK","On track",IF(H13="","Route to analyst review","Explained — driver documented")) -> On track
A15: Total | B15: =SUM(B6:B13) -> 424.32 | D15: =SUM(D6:D13) -> 414.3036 | E15: =SUM(E6:E13) -> -10.0164 | F15: =IF(B15=0,0,E15/B15) -> -0.023605769
A16: Flags | B16: =COUNTIF(G6:G13,"FLAG") -> 3
A17: Unexplained | B17: =COUNTIF(I6:I13,"Route to analyst review") -> 2

Sheet Memo
A1: Finance Point of View — Live Sports Package Partnership
A2: One page. Numbers in column B are linked to the model; replace bracketed text in column C with your conclusions.
A4: 1. RECOMMENDATION | C4: Sign only under Structure B (minimum guarantee + revenue share), with a lower or step-up MG and a performance exit after Year 2. B is the only structure with positive Base and probability-weighted NPV; the flat fee destroys value unless the Upside materializes, and pure revenue share hands the partner too much of the upside.
A5: Best structure — Base | B5: =Scenarios!C7 -> B: MG + revenue share
A6: Best structure — Prob-weighted | B6: =Scenarios!E7 -> B: MG + revenue share
A7: 2. KEY NUMBERS
A8: Prob-weighted NPV — A | B8: =Scenarios!E4 -> -192.88823
A9: Prob-weighted NPV — B | B9: =Scenarios!E5 -> 122.33117
A10: Prob-weighted NPV — C | B10: =Scenarios!E6 -> -52.861324
A11: Base NPV — B | B11: =Scenarios!C5 -> 101.48325
A12: Downside NPV — B | B12: =Scenarios!B5 -> -298.12206 | C12: In the Downside, deal contribution covers well under half of the MG each year — every structure loses money, so downside protection must come from contract terms.
A13: Base payback — B | B13: =Scenarios!C16 -> Year 3
A14: Breakeven Year-1 subscribers (mm) | B14: =Sensitivity!B13 -> 0.72272804 | C14: Roughly a quarter below the Base case of 1.0M — a real but thin cushion.
A15: Largest sensitivity driver | B15: =Sensitivity!B12 -> Year-1 subscribers | C15: Subscribers drive both subscription revenue and whether revenue share exceeds the MG. It is also the least certain input, so it should anchor deal protections.
A16: 3. WHAT HAS TO BE TRUE | C16: (1) Year-1 subscribers above the breakeven level; (2) live-sports CPMs hold in the premium range rather than compressing toward the ~$26 CTV average; (3) most viewing is incremental (cannibalization near 25% or lower).
A17: 4. RISKS & NEGOTIATION LEVERS | C17: Key risk: MG exposure in the Downside. Levers: lower Year-1/2 MG stepping up with subscriber milestones; exit or renegotiation right if Year-2 subscribers miss plan; trade a longer term for a lower revenue share. Strategic value (engagement, cross-sell to other subscriptions) is excluded and would only strengthen the case.
A18: 5. TRACKING PLAN | C18: Report quarterly vs. the business case: subscribers, viewing hours, CPM, incremental revenue. Flag variances beyond threshold; require a documented driver before commentary (see Variance_Tracking and variance_tracking.py).
